aiser/__init__.py
aiser/version.py
aiser/agent/__init__.py
aiser/agent/agent.py
aiser/ai_server/__init__.py
aiser/ai_server/ai_server.py
aiser/ai_server/authentication/__init__.py
aiser/ai_server/authentication/asymmetric_jwt_rest_authenticator.py
aiser/ai_server/authentication/non_functional_rest_authenticator.py
aiser/ai_server/authentication/rest_authenticator.py
aiser/ai_server/rest_ai_server/__init__.py
aiser/ai_server/rest_ai_server/rest_ai_server.py
aiser/ai_server_consumer/__init__.py
aiser/ai_server_consumer/ai_server_consumer.py
aiser/ai_server_consumer/predefined_consumers.py
aiser/config/__init__.py
aiser/config/ai_server_config.py
aiser/config/ai_server_env_variables.py
aiser/env_tools/__init__.py
aiser/env_tools/load_dotenv_if_available.py
aiser/identifiable_entities/__init__.py
aiser/identifiable_entities/identifiable_entity.py
aiser/knowledge_base/__init__.py
aiser/knowledge_base/knowledge_base.py
aiser/knowledge_base/semantic_search_result.py
aiser/models/__init__.py
aiser/models/chat_message.py
aiser/models/dtos.py
aiser/utils/__init__.py
aiser-0.6.1.dist-info/LICENSE
aiser-0.6.1.dist-info/METADATA
aiser-0.6.1.dist-info/WHEEL
aiser-0.6.1.dist-info/top_level.txt
aiser-0.6.1.dist-info/RECORD
