Metadata-Version: 2.1
Name: aiser
Version: 0.6.1
Summary: Python package to serve AI agents and knowledge bases for Penlight AI.
Home-page: https://github.com/penlight-ai/aiapi
Author: Penlight AI Inc.
Author-email: support@penlight.ai
License: Apache License 2.0
Classifier: Development Status :: 1 - Planning
Classifier: Intended Audience :: Developers
Classifier: License :: OSI Approved :: Apache Software License
Classifier: Programming Language :: Python :: 3.11
License-File: LICENSE
Requires-Dist: uvicorn
Requires-Dist: fastapi
Requires-Dist: pyjwt[crypto]
Requires-Dist: httpx
